murmuration/__init__.py
murmuration/aws.py
murmuration/gcm.py
murmuration/helpers.py
murmuration/kms.py
murmuration/kms_wrap.py
murmuration/kms_wrapped.py
murmuration/settings.py
murmuration-0.7.dist-info/METADATA
murmuration-0.7.dist-info/WHEEL
murmuration-0.7.dist-info/top_level.txt
murmuration-0.7.dist-info/zip-safe
murmuration-0.7.dist-info/RECORD
