Metadata-Version: 2.1
Name: murmuration
Version: 0.7
Summary: encryption primitives for use with aws
Home-page: https://github.com/angry-penguins/murmuration
Author: Preetam Shingavi
Author-email: p.shingavi@yahoo.com
License: BSD
Keywords: aws python encryption cryptography kms
Platform: UNKNOWN
Classifier: Development Status :: 5 - Production/Stable
Classifier: Intended Audience :: Developers
Classifier: Topic :: Software Development :: Libraries :: Python Modules
Classifier: Programming Language :: Python :: 3
Classifier: Programming Language :: Python :: 3.6
Classifier: Programming Language :: Python :: 3.7
Classifier: License :: OSI Approved :: BSD License
Classifier: Topic :: Security :: Cryptography
Classifier: Topic :: Utilities
Requires-Dist: boto3 (>=1.9.0)
Requires-Dist: pycryptodome (>=3.7.3)
